<annotation>
  <folder>VOC2007</folder>
  <filename>2fb0ea080945fe86.jpg</filename>
  <source>
    <database>Coco database</database>
  </source>
  <size>
    <width>1024</width>
    <height>688</height>
    <depth>3</depth>
  </size>
  <segmented>0</segmented>
  <object>
    <name>Animal</name>
    <pose>Unspecified</pose>
    <truncated>0</truncated>
    <difficult>0</difficult>
    <bndbox>
      <xmin>61</xmin>
      <ymin>464</ymin>
      <xmax>117</xmax>
      <ymax>498</ymax>
    </bndbox>
  </object>
  <object>
    <name>Animal</name>
    <pose>Unspecified</pose>
    <truncated>0</truncated>
    <difficult>0</difficult>
    <bndbox>
      <xmin>205</xmin>
      <ymin>470</ymin>
      <xmax>240</xmax>
      <ymax>501</ymax>
    </bndbox>
  </object>
  <object>
    <name>Animal</name>
    <pose>Unspecified</pose>
    <truncated>0</truncated>
    <difficult>0</difficult>
    <bndbox>
      <xmin>485</xmin>
      <ymin>441</ymin>
      <xmax>529</xmax>
      <ymax>464</ymax>
    </bndbox>
  </object>
  <object>
    <name>Animal</name>
    <pose>Unspecified</pose>
    <truncated>0</truncated>
    <difficult>0</difficult>
    <bndbox>
      <xmin>610</xmin>
      <ymin>460</ymin>
      <xmax>656</xmax>
      <ymax>482</ymax>
    </bndbox>
  </object>
  <object>
    <name>Animal</name>
    <pose>Unspecified</pose>
    <truncated>0</truncated>
    <difficult>0</difficult>
    <bndbox>
      <xmin>722</xmin>
      <ymin>471</ymin>
      <xmax>773</xmax>
      <ymax>497</ymax>
    </bndbox>
  </object>
  <object>
    <name>Animal</name>
    <pose>Unspecified</pose>
    <truncated>0</truncated>
    <difficult>0</difficult>
    <bndbox>
      <xmin>922</xmin>
      <ymin>540</ymin>
      <xmax>996</xmax>
      <ymax>589</ymax>
    </bndbox>
  </object>
</annotation>
