<annotation>
  <folder>VOC2007</folder>
  <filename>cabaf198c8da6236.jpg</filename>
  <source>
    <database>Coco database</database>
  </source>
  <size>
    <width>1024</width>
    <height>768</height>
    <depth>3</depth>
  </size>
  <segmented>0</segmented>
  <object>
    <name>Animal</name>
    <pose>Unspecified</pose>
    <truncated>0</truncated>
    <difficult>0</difficult>
    <bndbox>
      <xmin>226</xmin>
      <ymin>182</ymin>
      <xmax>529</xmax>
      <ymax>389</ymax>
    </bndbox>
  </object>
  <object>
    <name>Animal</name>
    <pose>Unspecified</pose>
    <truncated>0</truncated>
    <difficult>0</difficult>
    <bndbox>
      <xmin>293</xmin>
      <ymin>170</ymin>
      <xmax>1022</xmax>
      <ymax>534</ymax>
    </bndbox>
  </object>
</annotation>
